Workbook

Sheet 收入表
A1: 日期 | B1: 客戶 | C1: 服務別 | D1: 金額（未稅） | E1: 金流管道 | F1: 綠界手續費 | G1: 實收金額 | I1: 說明：綠界手續費預設 2.75%，可依實際費率手動調整 F 欄公式（見 06_facts/platform_facts.md 查核後費率）
F2: =IF(E2="綠界",D2*0.0275,0) | G2: =D2-F2
F3: =IF(E3="綠界",D3*0.0275,0) | G3: =D3-F3
F4: =IF(E4="綠界",D4*0.0275,0) | G4: =D4-F4
F5: =IF(E5="綠界",D5*0.0275,0) | G5: =D5-F5
F6: =IF(E6="綠界",D6*0.0275,0) | G6: =D6-F6
F7: =IF(E7="綠界",D7*0.0275,0) | G7: =D7-F7
F8: =IF(E8="綠界",D8*0.0275,0) | G8: =D8-F8
F9: =IF(E9="綠界",D9*0.0275,0) | G9: =D9-F9
F10: =IF(E10="綠界",D10*0.0275,0) | G10: =D10-F10
F11: =IF(E11="綠界",D11*0.0275,0) | G11: =D11-F11
F12: =IF(E12="綠界",D12*0.0275,0) | G12: =D12-F12
F13: =IF(E13="綠界",D13*0.0275,0) | G13: =D13-F13
... F31: =IF(E31="綠界",D31*0.0275,0) | G31: =D31-F31
C33: 小計 | D33: =SUM(D2:D31) | F33: =SUM(F2:F31) | G33: =SUM(G2:G31)

Sheet 支出表
A1: 日期 | B1: 類別 | C1: 金額 | D1: 發票號
B33: 小計 | C33: =SUM(C2:C31)

Sheet 月報表
A1: 月報表（樞紐總覽）
A3: 月費目標（新台幣） | B3: 300000
A4: 本月總收入（未稅） | B4: =收入表!D33
A5: 本月總實收 | B5: =收入表!G33
A6: 本月總支出 | B6: =支出表!C33
A7: 毛利（實收 - 支出） | B7: =B5-B6
A8: 毛利率 | B8: =IF(B5=0,0,B7/B5)
A9: 月費目標達成率 | B9: =IF(B3=0,0,B4/B3)
A11: 各服務營收占比
A12: 服務別 | B12: 金額 | C12: 占比
A13: 海外房地產企業顧問 | B13: =SUMIF(收入表!C:C,A13,收入表!D:D) | C13: =IF($B$4=0,0,B13/$B$4)
A14: 逆向破解競業情報書 | B14: =SUMIF(收入表!C:C,A14,收入表!D:D) | C14: =IF($B$4=0,0,B14/$B$4)
A15: 履歷重構與面試技巧 | B15: =SUMIF(收入表!C:C,A15,收入表!D:D) | C15: =IF($B$4=0,0,B15/$B$4)
